PycharmZhongwenZhinanFix1/README.md
PycharmZhongwenZhinanFix1/__init__.py
PycharmZhongwenZhinanFix1/__main__.py
PycharmZhongwenZhinanFix1/file.epub
PycharmZhongwenZhinanFix1/index.html
PycharmZhongwenZhinanFix1/css/__init__.py
PycharmZhongwenZhinanFix1/css/annotations.css
PycharmZhongwenZhinanFix1/css/main.css
PycharmZhongwenZhinanFix1/css/normalize.css
PycharmZhongwenZhinanFix1/css/popup.css
PycharmZhongwenZhinanFix1/font/__init__.py
PycharmZhongwenZhinanFix1/font/fontello.eot
PycharmZhongwenZhinanFix1/font/fontello.svg
PycharmZhongwenZhinanFix1/font/fontello.ttf
PycharmZhongwenZhinanFix1/font/fontello.woff
PycharmZhongwenZhinanFix1/img/__init__.py
PycharmZhongwenZhinanFix1/img/annotator-glyph-sprite.png
PycharmZhongwenZhinanFix1/img/annotator-icon-sprite.png
PycharmZhongwenZhinanFix1/img/apple-touch-icon.png
PycharmZhongwenZhinanFix1/img/cancelfullscreen.png
PycharmZhongwenZhinanFix1/img/close.png
PycharmZhongwenZhinanFix1/img/fullscreen.png
PycharmZhongwenZhinanFix1/img/loader.gif
PycharmZhongwenZhinanFix1/img/menu-icon.png
PycharmZhongwenZhinanFix1/img/save.png
PycharmZhongwenZhinanFix1/img/saved.png
PycharmZhongwenZhinanFix1/img/settings-s.png
PycharmZhongwenZhinanFix1/img/settings.png
PycharmZhongwenZhinanFix1/img/star.png
PycharmZhongwenZhinanFix1/js/__init__.py
PycharmZhongwenZhinanFix1/js/epub.js
PycharmZhongwenZhinanFix1/js/epub.min.js
PycharmZhongwenZhinanFix1/js/epub.min.map
PycharmZhongwenZhinanFix1/js/hooks.min.js
PycharmZhongwenZhinanFix1/js/hooks.min.map
PycharmZhongwenZhinanFix1/js/reader.js
PycharmZhongwenZhinanFix1/js/reader.js.map
PycharmZhongwenZhinanFix1/js/reader.min.js
PycharmZhongwenZhinanFix1/js/reader.min.map
PycharmZhongwenZhinanFix1/js/hooks/__init__.py
PycharmZhongwenZhinanFix1/js/hooks/extensions/__init__.py
PycharmZhongwenZhinanFix1/js/hooks/extensions/highlight.js
PycharmZhongwenZhinanFix1/js/libs/__init__.py
PycharmZhongwenZhinanFix1/js/libs/jquery.min.js
PycharmZhongwenZhinanFix1/js/libs/localforage.min.js
pycharm_zhongwen_zhinan_fix1-2025.3.25.1.dist-info/METADATA
pycharm_zhongwen_zhinan_fix1-2025.3.25.1.dist-info/WHEEL
pycharm_zhongwen_zhinan_fix1-2025.3.25.1.dist-info/entry_points.txt
pycharm_zhongwen_zhinan_fix1-2025.3.25.1.dist-info/top_level.txt
pycharm_zhongwen_zhinan_fix1-2025.3.25.1.dist-info/RECORD
